{"tagline":"teamgrau does  Softwareproject Human-Centered Computing","google":"","note":"Don't delete this file! It's used internally to help with page regeneration.","name":"teamgrau.github.com","body":"### Welcome to teamgrau\r\nshort introduction....\r\n\r\n### Idea\r\nshort presentation of our project idea\r\n\r\n## Iterationplan\r\ntable with the iteration plan plus process indicator\r\n\r\n### Authors and Contributors\r\nteamgrau consists of mix of students from Berlin Frei Universität Berlin (FU) and Berlin University of Arts (UdK). Namely Valerian Blos (@valerianBlos UdK), Simon Wichman (@cellard0or FU) and Thomas Eichinger (@thomaseichinger FU).\r\n\r\n### Support or Contact\r\nHaving trouble with our software? Open an issue at https://github.com/teamgrau/teamgrau.github.com/issues"}